mclf/__init__.py
mclf/benchmarks/__init__.py
mclf/benchmarks/semistable.py
mclf/berkovich/__init__.py
mclf/berkovich/affinoid_domain.py
mclf/berkovich/berkovich_line.py
mclf/berkovich/berkovich_path.py
mclf/berkovich/berkovich_path_old.py
mclf/berkovich/berkovich_trees.py
mclf/berkovich/piecewise_affine_function.py
mclf/berkovich/type_V_points.py
mclf/berkovich/valuative_functions.py
mclf/curves/__init__.py
mclf/curves/morphisms_of_smooth_projective_curves.py
mclf/curves/picard_curves.py
mclf/curves/smooth_projective_curves.py
mclf/curves/superelliptic_curves.py
mclf/monkey/__init__.py
mclf/monkey/trac_24533.py
mclf/monkey/trac_25294.py
mclf/monkey/trac_25360.py
mclf/monkey/trac_25440.py
mclf/monkey/trac_25441.py
mclf/monkey/trac_26066.py
mclf/monkey/util.py
mclf/padic_extensions/__init__.py
mclf/padic_extensions/elements_of_fake_padic_completion.py
mclf/padic_extensions/fake_padic_completions.py
mclf/padic_extensions/fake_padic_embeddings.py
mclf/padic_extensions/fake_padic_extensions.py
mclf/padic_extensions/slope_factors.py
mclf/padic_extensions/weak_padic_galois_extensions.py
mclf/semistable_reduction/__init__.py
mclf/semistable_reduction/admissible_reduction.py
mclf/semistable_reduction/reduction_trees.py
mclf/semistable_reduction/semistable_models.py
mclf/semistable_reduction/superp_models.py
mclf-1.0.4.dist-info/METADATA
mclf-1.0.4.dist-info/RECORD
mclf-1.0.4.dist-info/WHEEL
mclf-1.0.4.dist-info/top_level.txt
