Metadata-Version: 2.1
Name: mclf
Version: 1.0.4
Summary: A Sage toolbox for computing with Models of Curves over Local Fields
Home-page: https://github.com/mclf/mclf
Author: Stefan Wewers, Julian Rüth
Author-email: stefan.wewers@uni-ulm.de
License: UNKNOWN
Platform: UNKNOWN
Classifier: Development Status :: 4 - Beta
Classifier: Intended Audience :: Science/Research
Classifier: License :: OSI Approved :: GNU General Public License v2 or later (GPLv2+)
Classifier: Programming Language :: Python :: 2
Classifier: Programming Language :: Python :: 3
Classifier: Topic :: Scientific/Engineering :: Mathematics
Classifier: Operating System :: OS Independent
Requires-Dist: patchy
